syntropy_sdk/__init__.py
syntropy_sdk/api_client.py
syntropy_sdk/configuration.py
syntropy_sdk/exceptions.py
syntropy_sdk/rest.py
syntropy_sdk/utils.py
syntropy_sdk/api/__init__.py
syntropy_sdk/api/agents_api.py
syntropy_sdk/api/analytics_api.py
syntropy_sdk/api/audit_api.py
syntropy_sdk/api/auth_api.py
syntropy_sdk/api/connections_api.py
syntropy_sdk/api/nac_api.py
syntropy_sdk/api/network_api.py
syntropy_sdk/api/notification_api.py
syntropy_sdk/api/rules_api.py
syntropy_sdk/api/sdn_agents_api.py
syntropy_sdk/models/__init__.py
syntropy_sdk/models/a_agent_status.py
syntropy_sdk/models/a_agent_warning.py
syntropy_sdk/models/a_data.py
syntropy_sdk/models/a_data_response.py
syntropy_sdk/models/access_token_order.py
syntropy_sdk/models/agent_connection_subnet_statuses.py
syntropy_sdk/models/agent_error_log_severity.py
syntropy_sdk/models/agent_filter_agent_status.py
syntropy_sdk/models/agent_locked_fields.py
syntropy_sdk/models/agent_log_labels.py
syntropy_sdk/models/agent_log_log.py
syntropy_sdk/models/agent_log_source.py
syntropy_sdk/models/agent_provider.py
syntropy_sdk/models/agent_provider_name_and_id.py
syntropy_sdk/models/agent_provider_order_string.py
syntropy_sdk/models/agent_service_subnet.py
syntropy_sdk/models/agent_service_types.py
syntropy_sdk/models/agent_services_update_changes.py
syntropy_sdk/models/agent_status.py
syntropy_sdk/models/agent_tag.py
syntropy_sdk/models/agent_type.py
syntropy_sdk/models/agent_wg_config.py
syntropy_sdk/models/any_of_v1_agent_order_items.py
syntropy_sdk/models/audit_action_type.py
syntropy_sdk/models/audit_log.py
syntropy_sdk/models/audit_record_type.py
syntropy_sdk/models/audit_source_type.py
syntropy_sdk/models/auth_source.py
syntropy_sdk/models/connection_service_agent_service_subnet.py
syntropy_sdk/models/connections_pointtotag_body.py
syntropy_sdk/models/coordinates_search_body.py
syntropy_sdk/models/get_user_invitation_response.py
syntropy_sdk/models/id_number.py
syntropy_sdk/models/iface_active.py
syntropy_sdk-0.4.3.dist-info/LICENSE
syntropy_sdk-0.4.3.dist-info/METADATA
syntropy_sdk-0.4.3.dist-info/WHEEL
syntropy_sdk-0.4.3.dist-info/top_level.txt
syntropy_sdk-0.4.3.dist-info/RECORD
