Metadata-Version: 2.1
Name: syntropy-sdk
Version: 0.4.3
Summary: Syntropy SDK for Python
Home-page: https://github.com/syntropynet/syntropy-python-sdk/
Author: Andrius Mikonis
Author-email: andrius@syntropynet.com
License: MIT
Platform: any
Classifier: Development Status :: 5 - Production/Stable
Classifier: Intended Audience :: Developers
Classifier: Natural Language :: English
Classifier: License :: OSI Approved :: MIT License
Classifier: Programming Language :: Python
Classifier: Programming Language :: Python :: 3.6
Classifier: Programming Language :: Python :: 3.7
Classifier: Programming Language :: Python :: 3.8
Requires-Python: >=3.6
License-File: LICENSE
Requires-Dist: certifi (>=14.05.14)
Requires-Dist: six (>=1.10)
Requires-Dist: python-dateutil (>=2.5.3)
Requires-Dist: setuptools (>=21.0.0)
Requires-Dist: urllib3 (>=1.15.1)
